mentormatch/__init__.py
mentormatch/application_schema.toml
mentormatch/api/__init__.py
mentormatch/api/app/app_main.py
mentormatch/api/app/setup_app_context.py
mentormatch/api/app/setup_compatibility_checker_factory.py
mentormatch/api/app/setup_sorter_context_mgr.py
mentormatch/api/applicant/__init__.py
mentormatch/api/applicant/applicant_abc.py
mentormatch/api/applicant/applicant_collection.py
mentormatch/api/applicant/applicant_factory.py
mentormatch/api/applicant/applicant_implementation_mentee.py
mentormatch/api/applicant/applicant_implementation_mentor.py
mentormatch/api/compatibility/__init__.py
mentormatch/api/compatibility/compatibility_checker_abc.py
mentormatch/api/compatibility/compatibility_checker_aggregator.py
mentormatch/api/compatibility/compatibility_checker_factory.py
mentormatch/api/compatibility/compatibility_checker_implementation.py
mentormatch/api/initializer/initializer_abc.py
mentormatch/api/initializer/initializer_implementation.py
mentormatch/api/matcher/__init__.py
mentormatch/api/matcher/matcher.py
mentormatch/api/pair/pair.py
mentormatch/api/sorter/__init__.py
mentormatch/api/sorter/sorter_abc.py
mentormatch/api/sorter/sorter_aggregator.py
mentormatch/api/sorter/sorter_context_mgr.py
mentormatch/api/sorter/sorter_implementation.py
mentormatch/api/sorter/util.py
mentormatch/api/summarize/__init__.py
mentormatch/api/summarize/summarize.py
mentormatch/exporter/__init__.py
mentormatch/exporter/exporter_abc.py
mentormatch/exporter/exporter_aggregator.py
mentormatch/exporter/exporter_implementation.py
mentormatch/exporter/exporter_pair_details.py
mentormatch/exporter/exporter_setup.py
mentormatch/importer/__init__.py
mentormatch/importer/importer_abc.py
mentormatch/importer/importer_aggregator.py
mentormatch/importer/importer_implementation_excel.py
mentormatch/importer/importer_implementation_excel_schema.py
mentormatch/importer/importer_implementation_toml.py
mentormatch/importer/importer_setup.py
mentormatch/importer/util.py
mentormatch-1.1.dist-info/entry_points.txt
mentormatch-1.1.dist-info/LICENSE
mentormatch-1.1.dist-info/WHEEL
mentormatch-1.1.dist-info/METADATA
mentormatch-1.1.dist-info/RECORD
