Metadata-Version: 2.1
Name: mentormatch
Version: 1.1
Summary: Pair mentors with mentees.
Home-page: https://github.com/jonathanchukinas/mentormatch
License: UNKNOWN
Author: Jonathan Chukinas
Author-email: chukinas@gmail.com
Requires-Python: >=3.6.3
Classifier: License :: OSI Approved :: MIT License
Classifier: Programming Language :: Python :: 3
Classifier: Programming Language :: Python :: 3.7
Classifier: Development Status :: 2 - Pre-Alpha
Classifier: Intended Audience :: Developers
Classifier: License :: OSI Approved :: MIT License
Classifier: Natural Language :: English
Classifier: Programming Language :: Python :: 3.6
Classifier: Programming Language :: Python :: 3.7
Classifier: Programming Language :: Python :: 3.8
Requires-Dist: click
Requires-Dist: fuzzytable==0.*
Requires-Dist: toml
Requires-Dist: pandas
Requires-Dist: pytest ; extra == "test"
Requires-Dist: pytest-cov ; extra == "test"
Requires-Dist: tox ; extra == "test"
Provides-Extra: test
